LICENSE
MANIFEST.in
README.rst
requirements.txt
setup.py
src/plotnow/__init__.py
src/plotnow/arguments.py
src/plotnow/console.py
src/plotnow/loader.py
src/plotnow/plots.py
src/plotnow.egg-info/PKG-INFO
src/plotnow.egg-info/SOURCES.txt
src/plotnow.egg-info/dependency_links.txt
src/plotnow.egg-info/entry_points.txt
src/plotnow.egg-info/requires.txt
src/plotnow.egg-info/top_level.txt
src/plotnow.egg-info/zip-safe
src/plotnow/rc/dark.rc
src/plotnow/rc/light.rc