Metadata-Version: 1.1
Name: plotnow
Version: 0.1.0
Summary: A terminal application which plot 2D data and generate a graph.
Home-page: https://github.com/lambdalisue/plotnow
Author: Alisue
Author-email: lambdalisue@hashnote.net
License: MIT
Download-URL: https://github.com/lambdalisue/plotnow/tarball/master
Keywords: matplotlib numpy scipy plot graph
Platform: UNKNOWN
Classifier: Development Status :: 3 - Alpha
Classifier: Intended Audience :: Developers
Classifier: License :: OSI Approved :: MIT License
Classifier: Programming Language :: Python
Classifier: Programming Language :: Python :: 3
